boxset/__init__.py
boxset/util.py
boxset-0.2.0.dist-info/WHEEL
boxset-0.2.0.dist-info/METADATA
boxset-0.2.0.dist-info/RECORD
